adapt/__init__.py
adapt/utils.py
adapt/feature_based/__init__.py
adapt/feature_based/_adda.py
adapt/feature_based/_coral.py
adapt/feature_based/_dann.py
adapt/feature_based/_fe.py
adapt/feature_based/_msda.py
adapt/instance_based/__init__.py
adapt/instance_based/_kliep.py
adapt/instance_based/_kmm.py
adapt/instance_based/_tradaboost.py
adapt/parameter_based/__init__.py
adapt/parameter_based/_regular.py
tests/__init__.py
tests/test_adda.py
tests/test_coral.py
tests/test_dann.py
tests/test_fe.py
tests/test_kliep.py
tests/test_kmm.py
tests/test_msda.py
tests/test_regular.py
tests/test_tradaboost.py
tests/test_utils.py
adaptation-0.1.0.dist-info/LICENSE.txt
adaptation-0.1.0.dist-info/METADATA
adaptation-0.1.0.dist-info/WHEEL
adaptation-0.1.0.dist-info/top_level.txt
adaptation-0.1.0.dist-info/RECORD
